pySpaMint/__init__.py
pySpaMint/cell_selection.py
pySpaMint/evaluation.py
pySpaMint/optimizers.py
pySpaMint/plotting.py
pySpaMint/prep_smurf.py
pySpaMint/preprocess.py
pySpaMint/spamint.py
pySpaMint/utils.py
spamint-0.0.3.dist-info/LICENSE
spamint-0.0.3.dist-info/METADATA
spamint-0.0.3.dist-info/WHEEL
spamint-0.0.3.dist-info/top_level.txt
spamint-0.0.3.dist-info/RECORD
