Metadata-Version: 2.1
Name: spamint
Version: 0.0.3
Summary: Deciphering more accurate cell-cell interactions by modeling cells and their interactions
Home-page: https://github.com/deepomicslab/SpaMint/tree/main
Author: Jingwan WANG
Author-email: wanwang6-c@my.cityu.edu.hk
License: MIT
License-File: LICENSE
Requires-Dist: loess==2.1.2
Requires-Dist: pandas==1.5.2
Requires-Dist: scipy==1.9.3
Requires-Dist: scanpy==1.9.8
Requires-Dist: numpy==1.22.0
